LICENSE.txt
MANIFEST.in
README.md
send.py
setup.py
whatsapp.py
pywhatsapp.egg-info/PKG-INFO
pywhatsapp.egg-info/SOURCES.txt
pywhatsapp.egg-info/dependency_links.txt
pywhatsapp.egg-info/requires.txt
pywhatsapp.egg-info/top_level.txt