Metadata-Version: 1.0
Name: pywhatsapp
Version: 0.0.4
Summary: Simple wrapper around yowsup to send a message or mediafile with whatsapp
Home-page: https://github.com/tax/pywhatsapp
Author: Paul Tax
Author-email: paultax@gmail.com
License: BSD licence, see LICENCE.txt
Platform: UNKNOWN
